edtrack/__init__.py
edtrack/cli.py
edtrack/core.py
edtrack-0.1.0.dist-info/METADATA
edtrack-0.1.0.dist-info/WHEEL
edtrack-0.1.0.dist-info/entry_points.txt
edtrack-0.1.0.dist-info/top_level.txt
edtrack-0.1.0.dist-info/RECORD
