Metadata-Version: 2.4
Name: edtrack
Version: 0.1.0
Summary: CLI Email & Site Tracker
Home-page: https://github.com/qylvrix/edtrack
Author: qylvrix
Classifier: Programming Language :: Python :: 3
Classifier: License :: OSI Approved :: MIT License
Classifier: Operating System :: OS Independent
Requires-Python: >=3.7
